mag_test/__init__.py
mag_test/bean/__init__.py
mag_test/bean/base_test.py
mag_test/bean/case.py
mag_test/bean/control.py
mag_test/bean/datacls.py
mag_test/bean/element_info.py
mag_test/bean/function.py
mag_test/bean/module.py
mag_test/bean/plan.py
mag_test/bean/report_info.py
mag_test/bean/step.py
mag_test/core/__init__.py
mag_test/core/app_driver.py
mag_test/finder/__init__.py
mag_test/finder/driver_finder_utils.py
mag_test/finder/element_finder.py
mag_test/finder/element_finder_utils.py
mag_test/finder/window_finder.py
mag_test/model/__init__.py
mag_test/model/action_type.py
mag_test/model/control_type.py
mag_test/model/init_status.py
mag_test/model/menu_type.py
mag_test/model/test_component_type.py
mag_test/model/test_result.py
mag_test/model/usage_status.py
mag_test/report/__init__.py
mag_test/report/report_style.py
mag_test/utils/__init__.py
mag_test/utils/element_utils.py
mag_test/utils/event_utils.py
mag_test/utils/excel_convertor.py
mag_test/utils/table_utils.py
mag_test/utils/tree_utils.py
mag_test/utils/win_app_utils.py
tests/__init__.py
tests/bean/__init__.py
tests/bean/test_element_info.py
mag_test-0.1.207.dist-info/METADATA
mag_test-0.1.207.dist-info/WHEEL
mag_test-0.1.207.dist-info/top_level.txt
mag_test-0.1.207.dist-info/RECORD
