Metadata-Version: 2.1
Name: mag_test
Version: 0.1.207
Summary: 测试工具包
Home-page: http://gitlab.magnetitech.com:8088/sources/frame/py-frame/mag_test.git
Author: xlcao
Author-email: xl_cao@hotmail.com
Classifier: Programming Language :: Python :: 3
Classifier: License :: OSI Approved :: MIT License
Classifier: Operating System :: OS Independent
Requires-Python: >=3.6
